streamlink/__init__.py
streamlink/__main__.py
streamlink/_version.py
streamlink/api.py
streamlink/buffers.py
streamlink/cache.py
streamlink/compat.py
streamlink/exceptions.py
streamlink/logger.py
streamlink/options.py
streamlink/py.typed
streamlink/user_input.py
streamlink/packages/__init__.py
streamlink/packages/requests_file.py
streamlink/plugin/__init__.py
streamlink/plugin/plugin.py
streamlink/plugin/api/__init__.py
streamlink/plugin/api/useragents.py
streamlink/plugin/api/validate.py
streamlink/plugin/api/websocket.py
streamlink/plugin/api/webbrowser/__init__.py
streamlink/plugin/api/webbrowser/aws_waf.py
streamlink/plugins/__init__.py
streamlink/plugins/_plugins.json
streamlink/plugins/abematv.py
streamlink/plugins/adultswim.py
streamlink/plugins/albavision.py
streamlink/plugins/aloula.py
streamlink/plugins/app17.py
streamlink/plugins/ard_live.py
streamlink/plugins/ard_mediathek.py
streamlink/plugins/artetv.py
streamlink/plugins/atpchallenger.py
streamlink/plugins/atresplayer.py
streamlink/plugins/bbciplayer.py
streamlink/plugins/bfmtv.py
streamlink/plugins/bigo.py
streamlink/plugins/bilibili.py
streamlink/plugins/blasttv.py
streamlink/plugins/blazetv.py
streamlink/plugins/bloomberg.py
streamlink/plugins/brightcove.py
streamlink/plugins/btv.py
streamlink/plugins/cbsnews.py
streamlink/plugins/cdnbg.py
streamlink/plugins/ceskatelevize.py
streamlink/plugins/chzzk.py
streamlink/plugins/cinergroup.py
streamlink/plugins/clubbingtv.py
streamlink/plugins/cmmedia.py
streamlink/plugins/cnbce.py
streamlink/plugins/cnews.py
streamlink/plugins/dailymotion.py
streamlink/plugins/dash.py
streamlink/plugins/delfi.py
streamlink/plugins/deutschewelle.py
streamlink/plugins/dlive.py
streamlink/plugins/dogan.py
streamlink/plugins/dogus.py
streamlink/plugins/douyin.py
streamlink/plugins/drdk.py
streamlink/plugins/earthcam.py
streamlink/plugins/euronews.py
streamlink/plugins/filmon.py
streamlink/plugins/goltelevision.py
streamlink/plugins/goodgame.py
streamlink-8.1.1.dist-info/licenses/LICENSE
streamlink-8.1.1.dist-info/METADATA
streamlink-8.1.1.dist-info/WHEEL
streamlink-8.1.1.dist-info/entry_points.txt
streamlink-8.1.1.dist-info/top_level.txt
streamlink-8.1.1.dist-info/RECORD
