Metadata-Version: 2.4
Name: streamlink
Version: 8.1.1
Summary: Streamlink is a command-line utility that extracts streams from various services and pipes them into a video player of choice.
Author: Streamlink
Author-email: streamlink@protonmail.com
License-Expression: BSD-2-Clause
Project-URL: Homepage, https://github.com/streamlink/streamlink
Project-URL: Documentation, https://streamlink.github.io/
Project-URL: Tracker, https://github.com/streamlink/streamlink/issues
Project-URL: Source, https://github.com/streamlink/streamlink
Project-URL: Funding, https://streamlink.github.io/latest/support.html
Classifier: Development Status :: 5 - Production/Stable
Classifier: Environment :: Console
Classifier: Intended Audience :: End Users/Desktop
Classifier: Operating System :: POSIX
Classifier: Operating System :: MacOS
Classifier: Operating System :: Microsoft :: Windows
Classifier: Programming Language :: Python :: 3
Classifier: Programming Language :: Python :: 3 :: Only
Classifier: Programming Language :: Python :: 3.10
Classifier: Programming Language :: Python :: 3.11
Classifier: Programming Language :: Python :: 3.12
Classifier: Programming Language :: Python :: 3.13
Classifier: Programming Language :: Python :: 3.14
Classifier: Topic :: Internet :: WWW/HTTP
Classifier: Topic :: Multimedia :: Sound/Audio
Classifier: Topic :: Multimedia :: Video
Classifier: Topic :: Utilities
Requires-Python: >=3.10
License-File: LICENSE
Requires-Dist: certifi
Requires-Dist: exceptiongroup; python_version < "3.11"
Requires-Dist: isodate
Requires-Dist: lxml<7,>=4.6.4
Requires-Dist: pycountry
Requires-Dist: pycryptodome<4,>=3.4.3
Requires-Dist: PySocks!=1.5.7,>=1.5.6
Requires-Dist: requests<3,>=2.30.0
Requires-Dist: trio<1,>=0.25.0; python_version >= "3.13"
Requires-Dist: trio<1,>=0.22.0; python_version < "3.13"
Requires-Dist: trio-websocket<1,>=0.9.0
Requires-Dist: urllib3<3,>=2.0.0
Requires-Dist: websocket-client<2,>=1.2.1
Provides-Extra: decompress
Requires-Dist: urllib3[brotli]<3,>=2.0.0; python_version >= "3.14" and extra == "decompress"
Requires-Dist: urllib3[brotli,zstd]<3,>=2.0.0; python_version < "3.14" and extra == "decompress"
Dynamic: license-file
